{"type":"FeatureCollection","features":[{"type":"Feature","properties":{"marker-color":"#7e7e7e","marker-symbol":"","Tipo":"BAZAR","Nombre":"CANDIDA","Imagen":"","TIPO":"BAZAR"},"geometry":{"type":"Point","coordinates":[-61.4294958114624,-30.99747592788568]}},{"type":"Feature","properties":{"marker-color":"#7e7e7e","marker-symbol":"","Tipo":"BAZAR","Nombre":"ESTELA","Imagen":"","TIPO":"BAZAR"},"geometry":{"type":"Point","coordinates":[-61.42908811569213,-30.995636579975343]}}]}