{"type":"FeatureCollection","features":[{"type":"Feature","properties":{"marker-color":"#7e7e7e","marker-symbol":"hospital","Tipo":"Centro de Salud","Nombre":"CAPS Ataliva\"Dr. Roger Ghigi\"","Imagen":""},"geometry":{"type":"Point","coordinates":[-61.43580436706543,-30.99556300532105]}}]}