{"type":"FeatureCollection","features":[{"type":"Feature","properties":{"marker-color":"#7e7e7e","marker-symbol":"","Tipo":"Comuna de Ataliva","Nombre":"Comuna de Ataliva","Imagen":""},"geometry":{"type":"Point","coordinates":[-61.43175959587097,-30.998616305774423]}}]}