{"type":"FeatureCollection","features":[{"type":"Feature","properties":{"marker-color":"#7e7e7e","marker-symbol":"dentist","Tipo":"CONSULTORIOS ODONTOLOGICOS","Nombre":"DRA BELEN CURZI","Imagen":""},"geometry":{"type":"Point","coordinates":[-61.432156562805176,-30.99504798115181]}},{"type":"Feature","properties":{"marker-color":"#7e7e7e","marker-symbol":"dentist","Tipo":"CONSULTORIOS ODONTOLOGICOS","Nombre":"SMILE","Imagen":""},"geometry":{"type":"Point","coordinates":[-61.42940998077392,-30.996261962245107]}}]}