{"type":"FeatureCollection","features":[{"type":"Feature","properties":{"marker-color":"#7e7e7e","marker-symbol":"","Tipo":"Càmara de seguridad","Nombre":"Càmara 1","Imagen":""},"geometry":{"type":"Point","coordinates":[-61.430708169937134,-30.996535565698615]}},{"type":"Feature","properties":{"marker-color":"#7e7e7e","marker-symbol":"","Tipo":"Càmara de Seguridad","Nombre":"Càmara  3","Imagen":""},"geometry":{"type":"Point","coordinates":[-61.42829418182373,-30.99691952888529]}},{"type":"Feature","properties":{"marker-color":"#7e7e7e","marker-symbol":"","Tipo":"Càmara de seguridad","Nombre":"Càmara 4","Imagen":""},"geometry":{"type":"Point","coordinates":[-61.419568955898285,-30.998285229727692]}},{"type":"Feature","properties":{"marker-color":"#7e7e7e","marker-symbol":"","Tipo":"Càmara de Seguridad","Nombre":"Càmara 5","Imagen":""},"geometry":{"type":"Point","coordinates":[-61.43434524536132,-31.00023488323445]}},{"type":"Feature","properties":{"marker-color":"#7e7e7e","marker-symbol":"","Tipo":"Càmara de Seguridad","Nombre":"Càmara 6","Imagen":""},"geometry":{"type":"Point","coordinates":[-61.43561124801635,-30.995746941850335]}},{"type":"Feature","properties":{"marker-color":"#7e7e7e","marker-symbol":"","Tipo":"Càmara de Seguridad","Nombre":"Càmara 2","Imagen":""},"geometry":{"type":"Point","coordinates":[-61.428326368331916,-30.996914930532917]}},{"type":"Feature","properties":{"marker-color":"#7e7e7e","marker-symbol":"","Tipo":"Càmara de Seguridad","Nombre":"Càmara 7","Imagen":""},"geometry":{"type":"Point","coordinates":[-61.431432366371155,-30.994008727485184]}},{"type":"Feature","properties":{"marker-color":"#7e7e7e","marker-symbol":"","Tipo":"Càmara de Seguridad","Nombre":"Càmara 8","Imagen":""},"geometry":{"type":"Point","coordinates":[-61.43184542655944,-30.998873808571656]}}]}