{"type":"FeatureCollection","features":[{"type":"Feature","properties":{"marker-color":"#7e7e7e","marker-symbol":"","Tipo":"METALURGICAS","Nombre":"SOLDADOR:PONTE","Imagen":"","TIPO":"METALURGICAS"},"geometry":{"type":"Point","coordinates":[-61.4188528060913,-30.998873808571656]}},{"type":"Feature","properties":{"marker-color":"#7e7e7e","marker-symbol":"","Tipo":"METALURGICA","Nombre":"SOLDADOR:SALTEÑO","Imagen":"","TIPO":"METALURGICA"},"geometry":{"type":"Point","coordinates":[-61.432929039001465,-30.993650044387604]}},{"type":"Feature","properties":{"marker-color":"#7e7e7e","marker-symbol":"","Tipo":"METALURGICA","Nombre":"SODADOR:RAINIERI","Imagen":"","TIPO":"METALURGICA"},"geometry":{"type":"Point","coordinates":[-61.423401832580566,-30.9978989728871]}},{"type":"Feature","properties":{"marker-color":"#7e7e7e","marker-symbol":"","Tipo":"METALURGICA","Nombre":"SOLDADOR:GODOY","Imagen":"","TIPO":"METALURGICA"},"geometry":{"type":"Point","coordinates":[-61.43155574798584,-30.998984166700474]}}]}