{"type":"FeatureCollection","features":[{"type":"Feature","properties":{"marker-color":"#7e7e7e","marker-symbol":"water","Tipo":"Planta potabilizadora de Agua","Nombre":"Agua Potale","Imagen":""},"geometry":{"type":"Point","coordinates":[-61.420698165893555,-30.99707127438914]}}]}