{"type":"FeatureCollection","features":[{"type":"Feature","properties":{"marker-color":"#7e7e7e","marker-symbol":"","Tipo":"FUMIGADORA","Nombre":"ABRIATTA","Imagen":"","TIPO":"FUMIGADORA"},"geometry":{"type":"Point","coordinates":[-61.430912017822266,-31.012759536610222]}},{"type":"Feature","properties":{"marker-color":"#7e7e7e","marker-symbol":"","Tipo":"FUMIGADORA","Nombre":"COOPERATIVA C.M.R.H.","Imagen":"","TIPO":"FUMIGADORA"},"geometry":{"type":"Point","coordinates":[-61.428787708282464,-31.011913576603828]}},{"type":"Feature","properties":{"marker-color":"#7e7e7e","marker-symbol":"","Tipo":"FUMIGADORA","Nombre":"HUG(CASA)","Imagen":"","TIPO":"FUMIGADORA"},"geometry":{"type":"Point","coordinates":[-61.430010795593255,-30.992031355168695]}}]}