{"type":"FeatureCollection","features":[{"type":"Feature","properties":{"marker-color":"#7e7e7e","marker-symbol":"dog-park","Tipo":"Veterinaria","Nombre":"Veterinaria \"Ataliva\"","Imagen":""},"geometry":{"type":"Point","coordinates":[-61.43356204032897,-30.997659860725587]}}]}