{"type":"FeatureCollection","features":[{"type":"Feature","properties":{"marker-color":"#aa6e6e","marker-symbol":"","Tipo":"","Nombre":"Policia","Telefono":101},"geometry":{"type":"Point","coordinates":[-62.714896202087395,-34.26640276005368]}}]}